{
  "customers": [
    {
      "客户名称": "华东精密制造",
      "行业": "制造",
      "客户规模": "2000-10000人",
      "客户区域": "华东",
      "负责SA": "林晨",
      "商机阶段": "方案演示",
      "预计商机金额": 180,
      "客户意向等级": "S-重点推进",
      "重点诉求": ["现场管理", "流程提效", "数据看板", "AI 助理"],
      "客户痛点": "设备巡检依赖纸质记录，异常响应慢，管理层无法实时看到产线风险。",
      "决策链成熟度": "业务Owner明确",
      "客户状态": "高风险"
    },
    {
      "客户名称": "北方连锁零售",
      "行业": "零售",
      "客户规模": "500-2000人",
      "客户区域": "华北",
      "负责SA": "周岚",
      "商机阶段": "需求确认",
      "预计商机金额": 90,
      "客户意向等级": "A-高意向",
      "重点诉求": ["移动协同", "流程提效", "数据看板"],
      "客户痛点": "总部无法及时掌握门店巡检和整改状态，区域排名和复盘依赖人工汇总。",
      "决策链成熟度": "业务Owner明确",
      "客户状态": "活跃推进"
    },
    {
      "客户名称": "政务协同中心",
      "行业": "政企",
      "客户规模": "2000-10000人",
      "客户区域": "华东",
      "负责SA": "陈越",
      "商机阶段": "Demo/POC",
      "预计商机金额": 260,
      "客户意向等级": "S-重点推进",
      "重点诉求": ["流程提效", "权限治理", "数据看板"],
      "客户痛点": "督办事项跨部门推进难，领导看不到真实进度，数据权限边界复杂。",
      "决策链成熟度": "IT参与",
      "客户状态": "高风险"
    }
  ],
  "solutionPackages": [
    {
      "方案名称": "制造业设备巡检与异常闭环",
      "行业": "制造",
      "适用场景": ["巡检", "工单", "经营看板", "AI助理"],
      "成熟度等级": "S-可直接演示交付",
      "成熟度评分": 92,
      "OpenYida覆盖度": 92,
      "客户问题": "巡检记录分散、异常无法闭环、维修响应慢、管理层缺少实时驾驶舱。",
      "价值主张": "让一线异常上报、维修派单、验收评价和管理看板形成闭环。",
      "交付资产": ["客户PPT", "演示话术", "PRD", "FAQ", "验收清单"]
    },
    {
      "方案名称": "零售门店巡检与整改闭环",
      "行业": "零售",
      "适用场景": ["巡检", "督办", "经营看板"],
      "成熟度等级": "A-可演示需少量客户化",
      "成熟度评分": 86,
      "OpenYida覆盖度": 82,
      "客户问题": "门店执行标准不统一，整改缺少闭环，区域管理依赖人工统计。",
      "价值主张": "总部标准下发、门店移动填报、区域整改督办和排行复盘一体化。",
      "交付资产": ["客户PPT", "演示话术", "FAQ"]
    },
    {
      "方案名称": "政企督办事项闭环",
      "行业": "政企",
      "适用场景": ["督办", "审批", "经营看板", "权限治理"],
      "成熟度等级": "A-可演示需少量客户化",
      "成熟度评分": 85,
      "OpenYida覆盖度": 78,
      "客户问题": "跨部门事项责任不清，进度上报不及时，领导驾驶舱缺少可信数据。",
      "价值主张": "把会议纪要、责任拆解、部门协同、超期预警和领导看板打通。",
      "交付资产": ["客户PPT", "演示话术", "PRD", "风险说明"]
    }
  ],
  "visits": [
    {
      "客户名称": "华东精密制造",
      "负责SA": "林晨",
      "拜访时间": "2026-05-13 14:00",
      "拜访类型": "方案演示",
      "拜访状态": "已准备",
      "拜访目标": "演示设备巡检异常闭环，确认维修派单和驾驶舱指标。",
      "推荐方案": "制造业设备巡检与异常闭环",
      "Demo状态": "已创建",
      "风险标签": ["决策链"],
      "AI需求摘要": "客户重点关注产线异常闭环、维修响应 SLA 和管理层看板。"
    },
    {
      "客户名称": "北方连锁零售",
      "负责SA": "周岚",
      "拜访时间": "2026-05-14 10:30",
      "拜访类型": "需求访谈",
      "拜访状态": "待准备",
      "拜访目标": "梳理门店巡检、整改督办和区域排行诉求。",
      "推荐方案": "零售门店巡检与整改闭环",
      "Demo状态": "未创建",
      "风险标签": ["预算"],
      "AI需求摘要": "客户业务侧意愿明确，但总部预算周期和 owner 尚不清晰。"
    },
    {
      "客户名称": "政务协同中心",
      "负责SA": "陈越",
      "拜访时间": "2026-05-15 16:00",
      "拜访类型": "Demo演示",
      "拜访状态": "方案确认中",
      "拜访目标": "确认督办事项闭环、领导驾驶舱和数据权限边界。",
      "推荐方案": "政企督办事项闭环",
      "Demo状态": "需改版",
      "风险标签": ["交付边界", "系统集成复杂"],
      "AI需求摘要": "POC 范围扩大，需要主管和行业专家共同确认交付边界。"
    }
  ],
  "demoInstances": [
    {
      "Demo名称": "华东精密制造设备巡检 Demo",
      "客户名称": "华东精密制造",
      "关联方案": "制造业设备巡检与异常闭环",
      "创建人": "林晨",
      "Demo状态": "已创建",
      "创建耗时": 8,
      "创建时间": "2026-05-12 16:20",
      "最近演示时间": "2026-05-13 14:00",
      "演示反馈": "客户认可移动巡检和异常闭环，希望增加设备台账导入和维修 SLA。"
    },
    {
      "Demo名称": "政务督办事项闭环 Demo",
      "客户名称": "政务协同中心",
      "关联方案": "政企督办事项闭环",
      "创建人": "陈越",
      "Demo状态": "需改版",
      "创建耗时": 12,
      "创建时间": "2026-05-10 11:30",
      "最近演示时间": "2026-05-15 16:00",
      "演示反馈": "客户要求增加多部门权限隔离和领导驾驶舱按部门穿透。"
    }
  ],
  "meetingNotes": [
    {
      "客户名称": "华东精密制造",
      "负责SA": "林晨",
      "会议时间": "2026-05-13 15:20",
      "来源": "钉钉闪记",
      "原始纪要": "客户希望先围绕设备巡检、异常上报、维修派单、验收评价形成闭环，后续再扩展设备台账。",
      "AI需求摘要": "制造客户需要移动巡检、异常闭环、维修 SLA 和管理驾驶舱，现场 Demo 已验证核心链路。",
      "客户异议": "客户 IT 担心设备主数据导入和权限隔离成本。",
      "推荐方案理由": "制造业设备巡检方案覆盖巡检、工单、看板和 AI 总结，可通过 OpenYida 快速交付样板间。"
    },
    {
      "客户名称": "政务协同中心",
      "负责SA": "陈越",
      "会议时间": "2026-05-15 17:10",
      "来源": "钉钉会议",
      "原始纪要": "客户要求督办事项能够按部门分权、按领导视角汇总，并支持与既有系统进行数据同步。",
      "AI需求摘要": "政企客户关注督办闭环、权限边界、领导驾驶舱和系统集成范围，需要冻结 POC 边界。",
      "客户异议": "客户希望一次性纳入多个系统，交付范围存在扩大风险。",
      "推荐方案理由": "政企督办闭环方案适合作为 POC 主线，先证明会议纪要到责任拆解再到领导看板的闭环价值。"
    }
  ],
  "weeklyReports": [
    {
      "SA": "林晨",
      "活跃客户数": 18,
      "本周拜访数": 9,
      "方案演示数": 5,
      "Demo创建数": 4,
      "高风险客户数": 1,
      "拜访前准备率": 92,
      "会后纪要沉淀率": 88,
      "下一步明确率": 86,
      "需要主管支持": "华东精密制造需要主管陪访，帮助客户明确 IT、生产、采购三方决策链。"
    },
    {
      "SA": "周岚",
      "活跃客户数": 15,
      "本周拜访数": 8,
      "方案演示数": 3,
      "Demo创建数": 2,
      "高风险客户数": 3,
      "拜访前准备率": 80,
      "会后纪要沉淀率": 72,
      "下一步明确率": 76,
      "需要主管支持": "北方连锁零售预算周期较长，需要确认总部业务 owner 和 IT 侧评估窗口。"
    },
    {
      "SA": "陈越",
      "活跃客户数": 12,
      "本周拜访数": 6,
      "方案演示数": 4,
      "Demo创建数": 3,
      "高风险客户数": 2,
      "拜访前准备率": 84,
      "会后纪要沉淀率": 82,
      "下一步明确率": 78,
      "需要主管支持": "政务协同中心 POC 范围持续扩大，需要行业专家和主管共同冻结边界。"
    }
  ],
  "riskCustomers": [
    {
      "客户名称": "华东精密制造",
      "负责SA": "林晨",
      "风险等级": "高风险",
      "风险类型": ["决策链缺失"],
      "当前阶段": "方案演示",
      "风险原因": "已演示 Demo，但客户侧 IT 和生产负责人尚未共同确认。",
      "AI建议动作": "建议主管陪访，并要求客户明确 IT、生产、采购三方决策链。",
      "需要主管介入": "是",
      "处理状态": "待处理"
    },
    {
      "客户名称": "政务协同中心",
      "负责SA": "陈越",
      "风险等级": "高风险",
      "风险类型": ["交付边界不清", "集成复杂"],
      "当前阶段": "Demo/POC",
      "风险原因": "客户不断扩大 POC 范围，涉及多个系统和权限边界。",
      "AI建议动作": "建议行业专家介入，先冻结 POC 范围，再评估集成工作量。",
      "需要主管介入": "是",
      "处理状态": "处理中"
    }
  ]
}
